comfyui_workflow_generator/__init__.py
comfyui_workflow_generator/cli.py
comfyui_workflow_generator/executor.py
comfyui_workflow_generator/generator.py
comfyui_workflow_generator-0.1.0.dist-info/licenses/LICENSE
sandbox/antlers_weird_workflow.py
sandbox/my_test.py
sandbox/workflow_api.py
venv/bin/activate_this.py
comfyui_workflow_generator-0.1.0.dist-info/METADATA
comfyui_workflow_generator-0.1.0.dist-info/WHEEL
comfyui_workflow_generator-0.1.0.dist-info/entry_points.txt
comfyui_workflow_generator-0.1.0.dist-info/top_level.txt
comfyui_workflow_generator-0.1.0.dist-info/RECORD
