Metadata-Version: 2.4
Name: comfyui-workflow-generator
Version: 0.1.0
Summary: A Python package for generating ComfyUI workflow APIs from object_info.json using AST code generator
Author-email: Owl <lonelyowl13@gmail.com>
License-Expression: WTFPL
Project-URL: Homepage, https://github.com/lonelyowl13/comfyui-workflow-generator
Project-URL: Repository, https://github.com/lonelyowl13/comfyui-workflow-generator
Project-URL: Issues, https://github.com/lonelyowl13/comfyui-workflow-generator/issues
Classifier: Development Status :: 3 - Alpha
Classifier: Intended Audience :: Developers
Classifier: Operating System :: OS Independent
Classifier: Programming Language :: Python :: 3
Classifier: Programming Language :: Python :: 3.8
Classifier: Programming Language :: Python :: 3.9
Classifier: Programming Language :: Python :: 3.10
Classifier: Programming Language :: Python :: 3.11
Classifier: Programming Language :: Python :: 3.12
Requires-Python: >=3.8
License-File: LICENSE
Requires-Dist: requests>=2.25.0
Requires-Dist: astor>=0.8.0
Provides-Extra: dev
Requires-Dist: pytest>=6.0; extra == "dev"
Requires-Dist: black>=21.0; extra == "dev"
Requires-Dist: flake8>=3.8; extra == "dev"
Requires-Dist: mypy>=0.900; extra == "dev"
Dynamic: license-file
